streamlit_stackoverflow/make_plots.py
streamlit_stackoverflow/question_one.py
streamlit_stackoverflow/question_two.py
streamlit_stackoverflow/streamlit_app.py
streamlit_stackoverflow-0.1.2.dist-info/WHEEL
streamlit_stackoverflow-0.1.2.dist-info/METADATA
streamlit_stackoverflow-0.1.2.dist-info/RECORD
