Metadata-Version: 2.1
Name: streamlit-stackoverflow
Version: 0.1.2
Summary: Project created to learning Streamlit.
Author: Joao Corte
Author-email: jpaulorc@gmail.com
Requires-Python: >=3.9,<3.11
Classifier: Programming Language :: Python :: 3
Classifier: Programming Language :: Python :: 3.10
Classifier: Programming Language :: Python :: 3.9
Requires-Dist: matplotlib (>=3.5.1,<4.0.0)
Requires-Dist: numpy (==1.21.4)
Requires-Dist: pandas (>=1.3.5,<2.0.0)
Requires-Dist: plotly (>=5.4.0,<6.0.0)
Requires-Dist: pywaffle (>=0.6.3,<0.7.0)
Requires-Dist: seaborn (>=0.11.2,<0.12.0)
Requires-Dist: streamlit (>=1.2.0,<2.0.0)
